ario3s_aiva/__init__.py
ario3s_aiva/__main__.py
ario3s_aiva/commands/__init__.py
ario3s_aiva/commands/change_server.py
ario3s_aiva/commands/connect.py
ario3s_aiva/commands/disconnect.py
ario3s_aiva/commands/list_servers.py
ario3s_aiva/commands/restart.py
ario3s_aiva/commands/status.py
ario3s_aiva/config.py
ario3s_aiva/main.py
ario3s_aiva/utils/__init__.py
ario3s_aiva/utils/config_file.py
ario3s_aiva/utils/os_commands.py
ario3s_aiva/utils/run_command.py
ario3s_aiva/version.py
ario3s_aiva-1.0.6.dist-info/entry_points.txt
ario3s_aiva-1.0.6.dist-info/METADATA
ario3s_aiva-1.0.6.dist-info/WHEEL
ario3s_aiva-1.0.6.dist-info/RECORD
