Metadata-Version: 2.1
Name: ario3s-aiva
Version: 1.0.6
Summary: Manage dynamic ssh tunnel on localhost
Author: ario
Author-email: cybera.3s@gmail.com
Requires-Python: >=3.10,<4.0
Classifier: Programming Language :: Python :: 3
Classifier: Programming Language :: Python :: 3.10
Classifier: Programming Language :: Python :: 3.11
Requires-Dist: toml (>=0.10.2,<0.11.0)
Requires-Dist: tomli (>=2.0.1,<3.0.0)
Requires-Dist: typer[all] (>=0.7.0,<0.8.0)
Project-URL: repository, https://github.com/cybera3s/ario3s_aiva_cli
